{
  "project_info": {
    "project_number": "605928001302",
    "project_id": "ecosim-v1",
    "storage_bucket": "ecosim-v1.appspot.com"
  },
  "client": [
    {
      "client_info": {
        "mobilesdk_app_id": "1:605928001302:android:108c74347ffcafb436ca37",
        "android_client_info": {
          "package_name": "com.ecosim"
        }
      },
      "oauth_client": [
        {
          "client_id": "605928001302-004mskg40n7pvu5nu31vh1768vtfancm.apps.googleusercontent.com",
          "client_type": 1,
          "android_info": {
            "package_name": "com.ecosim",
            "certificate_hash": "5e8f16062ea3cd2c4a0d547876baa6f38cabf625"
          }
        },
        {
          "client_id": "605928001302-qeqefdqrvaqf85imqm752vv32nb1rlbi.apps.googleusercontent.com",
          "client_type": 3
        }
      ],
      "api_key": [
        {
          "current_key": "AIzaSyCsuJX4I49dkhCp1N4aZ03sSY26UL3PJ3U"
        }
      ],
      "services": {
        "appinvite_service": {
          "other_platform_oauth_client": [
            {
              "client_id": "605928001302-qeqefdqrvaqf85imqm752vv32nb1rlbi.apps.googleusercontent.com",
              "client_type": 3
            }
          ]
        }
      }
    }
  ],
  "configuration_version": "1"
}